nemoai/__init__.py
nemoai/sample/__init__.py
nemoai/sample/math.py
nemoai-0.1.1.dist-info/METADATA
nemoai-0.1.1.dist-info/WHEEL
nemoai-0.1.1.dist-info/RECORD
