Metadata-Version: 2.1
Name: nemoai
Version: 0.1.1
Summary: 
Author: 김일태
Author-email: multicg@naver.com
Requires-Python: >=3.12,<4.0
Classifier: Programming Language :: Python :: 3
Classifier: Programming Language :: Python :: 3.12
Requires-Dist: fastapi (>=0.115.8,<0.116.0)
Requires-Dist: setuptools (>=75.8.1,<76.0.0)
Requires-Dist: sphinx (>=8.2.1,<9.0.0)
Requires-Dist: twine (>=6.1.0,<7.0.0)
Requires-Dist: uvicorn (>=0.34.0,<0.35.0)
